wand/__init__.py
wand/api.py
wand/color.py
wand/compat.py
wand/display.py
wand/drawing.py
wand/exceptions.py
wand/font.py
wand/image.py
wand/resource.py
wand/sequence.py
wand/version.py
wandex-0.4.5.data/data/README.rst
wandex-0.4.5.dist-info/METADATA
wandex-0.4.5.dist-info/RECORD
wandex-0.4.5.dist-info/WHEEL
wandex-0.4.5.dist-info/top_level.txt
